pagexdata/__init__.py
pagexdata/database.py
pagexdata/entities.py
pagexdata/services/__init__.py
pagexdata/services/database_service.py
pagexdata/services/datetime_service.py
pagex_stocks_data-0.0.65.dist-info/LICENSE
pagex_stocks_data-0.0.65.dist-info/METADATA
pagex_stocks_data-0.0.65.dist-info/WHEEL
pagex_stocks_data-0.0.65.dist-info/top_level.txt
pagex_stocks_data-0.0.65.dist-info/RECORD
