Metadata-Version: 2.1
Name: pagex-stocks-data
Version: 0.0.65
Summary: Data access layer for webby, pagex-stocks-api and stockwiz.
Home-page: https://github.com/raynic35/pagex-stocks-data
Author: Raymund Nickel
Author-email: raymundn@gmail.com
Project-URL: Bug Tracker, https://github.com/raynic35/pagex-stocks-data/issues
Classifier: Topic :: Software Development :: Libraries :: Python Modules
Requires-Python: >=3.6
License-File: LICENSE
Requires-Dist: SQLAlchemy (==1.4.27)
Requires-Dist: psycopg2 (==2.9.2)
Requires-Dist: pandas (==1.3.4)
Requires-Dist: pydantic (==1.10.2)
